README.md
setup.py
bcm/__init__.py
betterconsolemenu.egg-info/PKG-INFO
betterconsolemenu.egg-info/SOURCES.txt
betterconsolemenu.egg-info/dependency_links.txt
betterconsolemenu.egg-info/top_level.txt