Metadata-Version: 2.1
Name: betterconsolemenu
Version: 0.1a0
Summary: Console menu but better and fancy
Home-page: https://github.com/mas6y6/betterconsolemenu
Download-URL: https://github.com/mas6y6/betterconsolemenu/tree/main/dist
